MANIFEST.in
README.md
setup.py
dexy_guide_templates/__init__.py
dexy_guide_templates.egg-info/PKG-INFO
dexy_guide_templates.egg-info/SOURCES.txt
dexy_guide_templates.egg-info/dependency_links.txt
dexy_guide_templates.egg-info/requires.txt
dexy_guide_templates.egg-info/top_level.txt
dexy_guide_templates/cd-00-template/dexy.conf
dexy_guide_templates/cd-00-template/dexy.txt
dexy_guide_templates/cd-00-template/dexyplugin.py
dexy_guide_templates/cd-00-template/hello.txt
dexy_guide_templates/cd-hello-world-filter-template/dexy.yaml
dexy_guide_templates/cd-hello-world-filter-template/dexyplugin.py
dexy_guide_templates/cd-hello-world-filter-template/hello.txt
dexy_guide_templates/cd-settings-inheritance-template/dexy.yaml
dexy_guide_templates/cd-settings-inheritance-template/dexyplugin.py
dexy_guide_templates/cd-settings-inheritance-template/ex1.txt
dexy_guide_templates/cd-settings-inheritance-template/ex2.txt
dexy_guide_templates/cd-settings-inheritance-template/ex3.txt
dexy_guide_templates/cd-settings-inheritance-template/ex4.txt
dexy_guide_templates/gs-00-template/dexy.txt
dexy_guide_templates/gs-00-template/hello.txt
dexy_guide_templates/gs-01-template/dexy.txt
dexy_guide_templates/gs-01-template/hello.py
dexy_guide_templates/gs-01-template/hello.txt
dexy_guide_templates/gs-02-template/dexy.txt
dexy_guide_templates/gs-02-template/hello.py
dexy_guide_templates/gs-02-template/hello.txt
dexy_guide_templates/gs-03-template/dexy.txt
dexy_guide_templates/gs-03-template/hello.py
dexy_guide_templates/gs-03-template/hello.txt
dexy_guide_templates/gs-03-template/loop.py
dexy_guide_templates/gs-04-template/dexy.yaml
dexy_guide_templates/gs-04-template/hello.py
dexy_guide_templates/gs-04-template/hello.txt
dexy_guide_templates/gs-04-template/loop.py
dexy_guide_templates/gs-05-template/dexy.yaml
dexy_guide_templates/gs-05-template/doc.html
dexy_guide_templates/gs-05-template/script.py
dexy_guide_templates/gs-06-template/dexy.yaml
dexy_guide_templates/gs-06-template/doc.html
dexy_guide_templates/gs-06-template/script.py
dexy_guide_templates/gs-07-template/dexy.yaml
dexy_guide_templates/gs-07-template/doc.html
dexy_guide_templates/gs-07-template/script.py
